{
  "$schema": "http://json-schema.org/draft-07/schema#",
  "title": "21P-530EZ",
  "type": "object",
  "required": [],
  "properties": {
    "currentMailingAddressCity": {
      "type": "string",
      "x-va-field": {
        "label": "Current Mailing Address City",
        "widget": "text"
      }
    },
    "claimantsLastName": {
      "type": "string",
      "x-va-field": {
        "label": "Claimants Last Name",
        "widget": "text"
      }
    },
    "vafileNumber": {
      "type": "string",
      "x-va-field": {
        "label": "VA File Number",
        "widget": "text"
      }
    },
    "veteransSocialSecurityNumber": {
      "type": "string",
      "pattern": "^\\d{3}-?\\d{2}-?\\d{4}$",
      "maxLength": 11,
      "x-va-field": {
        "label": "Veterans Social Security Number",
        "widget": "ssn"
      }
    },
    "veteransLastName": {
      "type": "string",
      "x-va-field": {
        "label": "Veterans Last Name",
        "widget": "text"
      }
    },
    "place": {
      "type": "string",
      "x-va-field": {
        "label": "Place",
        "widget": "text"
      }
    },
    "serviceNumber": {
      "type": "string",
      "x-va-field": {
        "label": "Service Number",
        "widget": "text"
      }
    },
    "placeSeparated": {
      "type": "string",
      "x-va-field": {
        "label": "Place Separated",
        "widget": "text"
      }
    },
    "rating": {
      "type": "string",
      "x-va-field": {
        "label": "Rating",
        "widget": "text"
      }
    },
    "dateEnteredService": {
      "type": "string",
      "x-va-field": {
        "label": "Date Entered Service",
        "widget": "text"
      }
    },
    "dateSeparatedService": {
      "type": "string",
      "x-va-field": {
        "label": "Date Separated Service",
        "widget": "text"
      }
    },
    "veteransFirstName": {
      "type": "string",
      "x-va-field": {
        "label": "Veterans First Name",
        "widget": "text"
      }
    },
    "veteransMiddleInitial1": {
      "type": "string",
      "x-va-field": {
        "label": "Veterans Middle Initial",
        "widget": "text"
      }
    },
    "claimantsFirstName": {
      "type": "string",
      "x-va-field": {
        "label": "Claimants First Name",
        "widget": "text"
      }
    },
    "claimantsMiddleInitial1": {
      "type": "string",
      "x-va-field": {
        "label": "Claimants Middle Initial",
        "widget": "text"
      }
    },
    "currentMailingAddressNumberAndStreet": {
      "type": "string",
      "x-va-field": {
        "label": "Current Mailing Address Number and Street",
        "widget": "text"
      }
    },
    "currentMailingAddressApartmentOrUnitNumber": {
      "type": "string",
      "x-va-field": {
        "label": "Current Mailing Address Apartment or Unit Number",
        "widget": "text"
      }
    },
    "currentMailingAddressStateOrProvince": {
      "type": "string",
      "x-va-field": {
        "label": "Current Mailing Address State or Province",
        "widget": "text"
      }
    },
    "currentMailingAddressCountry": {
      "type": "string",
      "x-va-field": {
        "label": "Current Mailing Address Country",
        "widget": "text"
      }
    },
    "currentMailingAddressZiporPostalCode": {
      "type": "string",
      "pattern": "^\\d{5}(-\\d{4})?$",
      "x-va-field": {
        "label": "Current Mailing Address ZIP or Postal Code",
        "widget": "zip"
      }
    },
    "preferredEMailAddress": {
      "type": "string",
      "x-va-field": {
        "label": "Preferred Email Address",
        "widget": "text"
      }
    },
    "preferredTelephoneNumber": {
      "type": "string",
      "pattern": "^\\d{10}$",
      "x-va-field": {
        "label": "Preferred Telephone Number",
        "widget": "phone"
      }
    },
    "claimantsSocialSecurityNumber": {
      "type": "string",
      "pattern": "^\\d{3}-?\\d{2}-?\\d{4}$",
      "maxLength": 11,
      "x-va-field": {
        "label": "Claimants Social Security Number",
        "widget": "ssn"
      }
    },
    "otherName": {
      "type": "string",
      "x-va-field": {
        "label": "Other Name",
        "widget": "text"
      }
    },
    "nonServiceConnectedDeath": {
      "type": "boolean",
      "x-va-field": {
        "label": "Non Service Connected Death",
        "widget": "checkbox"
      }
    },
    "serviceConnectedDeath": {
      "type": "boolean",
      "x-va-field": {
        "label": "Service Connected Death",
        "widget": "checkbox"
      }
    },
    "unclaimedRemains": {
      "type": "boolean",
      "x-va-field": {
        "label": "Unclaimed Remains",
        "widget": "checkbox"
      }
    },
    "otherSpecify": {
      "type": "string",
      "x-va-field": {
        "label": "Other Specify",
        "widget": "text"
      }
    },
    "officialPosition": {
      "type": "string",
      "x-va-field": {
        "label": "Official Position",
        "widget": "text"
      }
    },
    "claimantSignature": {
      "type": "string",
      "x-va-field": {
        "label": "Claimant Signature",
        "widget": "text"
      }
    },
    "otherSpecify16": {
      "type": "string",
      "x-va-field": {
        "label": "Other Specify",
        "widget": "text"
      }
    },
    "numericField1": {
      "type": "string",
      "x-va-field": {
        "label": "Numeric Field",
        "widget": "text"
      }
    },
    "amountOfGovernmentOrEmployerContribution": {
      "type": "string",
      "x-va-field": {
        "label": "Amount of Government or Employer Contribution",
        "widget": "text"
      }
    },
    "placeOfDeath": {
      "type": "string",
      "x-va-field": {
        "label": "Place of Death",
        "widget": "text"
      }
    },
    "addressWitness1": {
      "type": "string",
      "x-va-field": {
        "label": "Address Witness",
        "widget": "text"
      }
    },
    "witnessSignature1": {
      "type": "string",
      "x-va-field": {
        "label": "Witness Signature",
        "widget": "text"
      }
    },
    "witnessSignature2": {
      "type": "string",
      "x-va-field": {
        "label": "Witness Signature",
        "widget": "text"
      }
    },
    "dateSigned": {
      "type": "string",
      "x-va-field": {
        "label": "Date Signed",
        "widget": "text"
      }
    },
    "request": {
      "type": "string",
      "x-va-field": {
        "label": "Request",
        "widget": "text"
      }
    },
    "feesForClaims": {
      "type": "string",
      "x-va-field": {
        "label": "FEES for claims",
        "widget": "text"
      }
    },
    "eligibleClaimantsWhoShouldFileAClaim": {
      "type": "string",
      "x-va-field": {
        "label": "ELIGIBLE CLAIMANTS (Who Should File A Claim)",
        "widget": "text"
      }
    },
    "estateWhen": {
      "type": "string",
      "x-va-field": {
        "label": "estate when",
        "widget": "text"
      }
    },
    "claimantSocialSecurityNumberAnd": {
      "type": "string",
      "x-va-field": {
        "label": "Claimant Social Security Number and",
        "widget": "text"
      }
    },
    "stateAgency": {
      "type": "string",
      "x-va-field": {
        "label": "state agency.",
        "widget": "text"
      }
    },
    "timeLimitForFilingAClaim": {
      "type": "string",
      "x-va-field": {
        "label": "Time Limit For Filing A Claim",
        "widget": "text"
      }
    },
    "beFiledWithin_2YearsAfterThe": {
      "type": "string",
      "x-va-field": {
        "label": "Be Filed Within_2Years After the",
        "widget": "text"
      }
    },
    "burialAllowance": {
      "type": "string",
      "x-va-field": {
        "label": "Burial Allowance",
        "widget": "text"
      }
    },
    "transportationReimbursement": {
      "type": "string",
      "x-va-field": {
        "label": "Transportation Reimbursement",
        "widget": "text"
      }
    },
    "proofOfDeathToAccompanyClaim": {
      "type": "string",
      "x-va-field": {
        "label": "Proof Of Death To Accompany Claim",
        "widget": "text"
      }
    },
    "serviceRecord": {
      "type": "string",
      "x-va-field": {
        "label": "Service Record",
        "widget": "text"
      }
    },
    "howToSubmitAClaim": {
      "type": "string",
      "x-va-field": {
        "label": "How To Submit A Claim",
        "widget": "text"
      }
    },
    "youMustSubmit": {
      "type": "string",
      "x-va-field": {
        "label": "You must submit",
        "widget": "text"
      }
    },
    "youMust": {
      "type": "string",
      "x-va-field": {
        "label": "You must",
        "widget": "text"
      }
    },
    "youHaveUpToOneYearFromThe": {
      "type": "string",
      "format": "date",
      "x-va-field": {
        "label": "You have up to one year from the",
        "widget": "date"
      }
    },
    "claimBeforeOneYearFromThe": {
      "type": "string",
      "format": "date",
      "x-va-field": {
        "label": "claim before one year from the",
        "widget": "date"
      }
    },
    "youAreStronglyEncouragedTo": {
      "type": "string",
      "x-va-field": {
        "label": "You are strongly encouraged to",
        "widget": "text"
      }
    },
    "whatYouNeedToDo": {
      "type": "string",
      "x-va-field": {
        "label": "What You Need To Do",
        "widget": "text"
      }
    },
    "whereToSendInformationAndEvidence": {
      "type": "string",
      "x-va-field": {
        "label": "Where To Send Information And Evidence",
        "widget": "text"
      }
    },
    "whatTheEvidenceMustShowToSupportYourClaim": {
      "type": "string",
      "x-va-field": {
        "label": "What The Evidence Must Show To Support Your Claim",
        "widget": "text"
      }
    },
    "costsAnd": {
      "type": "string",
      "x-va-field": {
        "label": "costs and",
        "widget": "radio"
      }
    },
    "howVaDeterminesTheEffective": {
      "type": "string",
      "format": "date",
      "x-va-field": {
        "label": "How VA Determines The Effective",
        "widget": "date"
      }
    },
    "burialBenefitsAreBasedOnThe": {
      "type": "string",
      "format": "date",
      "x-va-field": {
        "label": "Burial benefits are based on the",
        "widget": "date"
      }
    },
    "inDeterminingTheEffective": {
      "type": "string",
      "format": "date",
      "x-va-field": {
        "label": "in determining the effective",
        "widget": "date"
      }
    },
    "relationshipOfClaimantToDeceasedVeteranCheckOne": {
      "type": "string",
      "x-va-field": {
        "label": "Relationship Of Claimant To Deceased Veteran (Check One)",
        "widget": "text"
      }
    },
    "nameOfTheDeceasedVeteranFirstMiddleInitialLast": {
      "type": "string",
      "x-va-field": {
        "label": "NAME OF THE DECEASED VETERAN (First, Middle Initial, Last)",
        "widget": "text"
      }
    },
    "claimantSNameFirstMiddleInitialLast": {
      "type": "string",
      "x-va-field": {
        "label": "CLAIMANT'S NAME (First, Middle Initial, Last)",
        "widget": "text"
      }
    },
    "currentMailingAddressNumberAndStreetOrRuralRouteP": {
      "type": "string",
      "x-va-field": {
        "label": "CURRENT MAILING ADDRESS (Number and street or rural route, P",
        "widget": "address"
      }
    },
    "stateProvincecountryzipCodePostalCode": {
      "type": "string",
      "x-va-field": {
        "label": "State/ProvinceCountryZIP Code/Postal Code",
        "widget": "select"
      }
    },
    "city": {
      "type": "string",
      "x-va-field": {
        "label": "City",
        "widget": "text"
      }
    },
    "telephoneNumberIncludeAreaCode": {
      "type": "string",
      "pattern": "^\\d{10}$",
      "x-va-field": {
        "label": "TELEPHONE NUMBER (Include Area Code)",
        "widget": "phone"
      }
    },
    "eMailAddress": {
      "type": "string",
      "x-va-field": {
        "label": "E-Mail Address",
        "widget": "address"
      }
    },
    "claimantSDateOfBirthMmDdYyyySeeInstructionsFor": {
      "type": "string",
      "format": "date",
      "x-va-field": {
        "label": "CLAIMANT'S DATE OF BIRTH (MM/DD/YYYY) (See instructions for",
        "widget": "date"
      }
    },
    "claimantSSocialSecurityNumberSeeInstructionsForExce": {
      "type": "string",
      "pattern": "^\\d{3}-?\\d{2}-?\\d{4}$",
      "maxLength": 11,
      "x-va-field": {
        "label": "CLAIMANT'S SOCIAL SECURITY NUMBER (See instructions for exce",
        "widget": "ssn"
      }
    },
    "ifVeteranServedUnderNameOtherThanThatShownInItem_1": {
      "type": "string",
      "x-va-field": {
        "label": "If Veteran Served Under Name Other Than That Shown in Item_",
        "widget": "text"
      }
    },
    "important": {
      "type": "string",
      "x-va-field": {
        "label": "Important",
        "widget": "text"
      }
    },
    "veteranSDateOfBirthMmDdYyyy_5VeteranSDateOfDea": {
      "type": "string",
      "format": "date",
      "x-va-field": {
        "label": "Veteran's Date Of Birth (MM/DD/YYYY)5. Veteran's Date Of Dea",
        "widget": "date"
      }
    },
    "ifYouAreTheDeceasedVeteranSSpouseDidYouPreviously": {
      "type": "string",
      "x-va-field": {
        "label": "If You Are The Deceased Veteran's Spouse, Did You Previously",
        "widget": "text"
      }
    },
    "stateVeteransFacility": {
      "type": "string",
      "x-va-field": {
        "label": "State Veteran's Facility",
        "widget": "select"
      }
    },
    "have": {
      "type": "string",
      "x-va-field": {
        "label": "have",
        "widget": "radio"
      }
    },
    "placeOfBurialPlotIntermentSiteOrFinalRestingPlace": {
      "type": "string",
      "x-va-field": {
        "label": "Place Of Burial Plot, Interment Site, Or Final Resting Place",
        "widget": "text"
      }
    },
    "otherSpecify2": {
      "type": "string",
      "x-va-field": {
        "label": "OTHER (Specify)",
        "widget": "text"
      }
    },
    "wasTheVeteranBuriedInANationalCemeteryOrOne": {
      "type": "string",
      "x-va-field": {
        "label": "Was The Veteran Buried In A National Cemetery, Or One",
        "widget": "text"
      }
    },
    "wasTheVeteranBuriedInACemeteryOwnedByTheStateOrT": {
      "type": "string",
      "x-va-field": {
        "label": "Was The Veteran Buried In A Cemetery Owned By The State Or T",
        "widget": "select"
      }
    },
    "name": {
      "type": "string",
      "x-va-field": {
        "label": "Name",
        "widget": "text"
      }
    },
    "areYouResponsibleForTheVeteranSPlotOrIntermentExpe": {
      "type": "string",
      "x-va-field": {
        "label": "Are You Responsible For The Veteran's Plot Or Interment Expe",
        "widget": "text"
      }
    },
    "areYouResponsibleForTheVeteranSTransportationExpense": {
      "type": "string",
      "x-va-field": {
        "label": "Are You Responsible For The Veteran's Transportation Expense",
        "widget": "text"
      }
    },
    "29b": {
      "type": "string",
      "format": "date",
      "x-va-field": {
        "label": "29b",
        "widget": "date"
      }
    },
    "dob": {
      "type": "string",
      "format": "date",
      "x-va-field": {
        "label": "DOB"
      }
    },
    "dateOfBirth": {
      "type": "string",
      "format": "date",
      "x-va-field": {
        "label": "Date of Birth"
      }
    },
    "dateOfDeath": {
      "type": "string",
      "format": "date",
      "x-va-field": {
        "label": "Date of Death"
      }
    },
    "dateOfBurial": {
      "type": "string",
      "format": "date",
      "x-va-field": {
        "label": "Date of Burial"
      }
    }
  },
  "x-va-metadata": {
    "formUrl": "https://www.vba.va.gov/pubs/forms/vba-21p-530ez-are.pdf",
    "status": "digitized",
    "totalFields": 110,
    "composedFields": 91,
    "coveragePercent": 100,
    "xfaLabelCount": 0,
    "needsReviewCount": 0,
    "pageCount": 8,
    "generatedAt": "2026-03-28T17:33:37.808Z",
    "postProcessedAt": "2026-03-30T20:02:41.719995+00:00",
    "redigitizedAt": "2026-03-30T20:37:25.699Z",
    "extractionSources": [
      "acroform",
      "acroform+text-inference",
      "text-inference"
    ],
    "fieldNameFixedAt": "2026-03-30T22:42:36.382149+00:00"
  }
}