{
  "$schema": "http://json-schema.org/draft-07/schema#",
  "title": "22-8794",
  "type": "object",
  "properties": {
    "address": {
      "type": "object",
      "properties": {
        "street": {
          "type": "string",
          "maxLength": 50
        },
        "street2": {
          "type": [
            "string",
            "null"
          ],
          "maxLength": 50
        },
        "city": {
          "type": "string",
          "maxLength": 30
        },
        "state": {
          "type": "string",
          "maxLength": 2
        },
        "postalCode": {
          "type": "string",
          "maxLength": 10
        },
        "country": {
          "type": [
            "string",
            "null"
          ],
          "maxLength": 30
        }
      },
      "required": [
        "street",
        "city",
        "state",
        "postalCode"
      ]
    },
    "phoneNumber": {
      "type": "string",
      "pattern": "^\\d{10}$",
      "maxLength": 10
    },
    "email": {
      "type": "string",
      "format": "email"
    },
    "date": {
      "type": "string",
      "format": "date"
    },
    "signature": {
      "type": "boolean",
      "description": "Signature certification"
    },
    "radioButtonList": {
      "type": "string"
    },
    "title": {
      "type": "string"
    },
    "jf01": {
      "type": "string"
    },
    "vaFacilityCode": {
      "type": "string"
    },
    "name": {
      "type": "string"
    },
    "printNameAndTitle": {
      "type": "string"
    },
    "remarks": {
      "type": "string"
    }
  },
  "x-va-metadata": {
    "formUrl": "https://www.vba.va.gov/pubs/forms/vba-22-8794-are.pdf",
    "status": "digitized",
    "totalFields": 68,
    "composedFields": 45,
    "coveragePercent": 66,
    "xfaLabelCount": 0,
    "needsReviewCount": 0,
    "pageCount": 3,
    "generatedAt": "2026-03-28T17:34:45.852Z"
  }
}