{
  "$schema": "http://json-schema.org/draft-07/schema#",
  "title": "26-6393",
  "type": "object",
  "required": [],
  "properties": {
    "recommendApplicationApproved": {
      "type": "boolean",
      "x-va-field": {
        "label": "Recommend Application Approved",
        "widget": "checkbox"
      }
    },
    "recommendApplicationDisapproved": {
      "type": "boolean",
      "x-va-field": {
        "label": "Recommend Application Disapproved",
        "widget": "checkbox"
      }
    },
    "nameOfBorrower": {
      "type": "string",
      "x-va-field": {
        "label": "Name of Borrower",
        "widget": "text"
      }
    },
    "amountOfLoan": {
      "type": "string",
      "x-va-field": {
        "label": "Amount of Loan",
        "widget": "text"
      }
    },
    "cashDownPaymentOnPurchasePrice": {
      "type": "string",
      "x-va-field": {
        "label": "Cash Down Payment on Purchase Price",
        "widget": "text"
      }
    },
    "occupationOfApplicant": {
      "type": "string",
      "x-va-field": {
        "label": "Occupation of Applicant",
        "widget": "text"
      }
    },
    "numberOfYearsAtPresentEmploymentApplicant": {
      "type": "string",
      "x-va-field": {
        "label": "Number of Years at Present Employment Applicant",
        "widget": "text"
      }
    },
    "liquidAssets": {
      "type": "string",
      "x-va-field": {
        "label": "Liquid Assets",
        "widget": "text"
      }
    },
    "currentMonthlyHousingExpense": {
      "type": "string",
      "x-va-field": {
        "label": "Current Monthly Housing Expense",
        "widget": "text"
      }
    },
    "numberOfYearsAtPresentEmploymentSpouse": {
      "type": "string",
      "x-va-field": {
        "label": "Number of Years at Present Employment Spouse",
        "widget": "text"
      }
    },
    "occupationOfSpouse": {
      "type": "string",
      "x-va-field": {
        "label": "Occupation of Spouse",
        "widget": "text"
      }
    },
    "ageOfDependents": {
      "type": "string",
      "x-va-field": {
        "label": "Age of Dependents",
        "widget": "text"
      }
    },
    "dateSigned": {
      "type": "string",
      "x-va-field": {
        "label": "Date Signed",
        "widget": "text"
      }
    },
    "borrower43": {
      "type": "string",
      "x-va-field": {
        "label": "Borrower",
        "widget": "text"
      }
    },
    "termOfLoanYrs": {
      "type": "string",
      "x-va-field": {
        "label": "Term of Loan Yrs",
        "widget": "text"
      }
    },
    "amount15": {
      "type": "string",
      "x-va-field": {
        "label": "Amount",
        "widget": "text"
      }
    },
    "amount16": {
      "type": "string",
      "x-va-field": {
        "label": "Amount",
        "widget": "text"
      }
    },
    "amount17": {
      "type": "string",
      "x-va-field": {
        "label": "Amount",
        "widget": "text"
      }
    },
    "amount18": {
      "type": "string",
      "x-va-field": {
        "label": "Amount",
        "widget": "text"
      }
    },
    "amount19": {
      "type": "string",
      "x-va-field": {
        "label": "Amount",
        "widget": "text"
      }
    },
    "amount20": {
      "type": "string",
      "x-va-field": {
        "label": "Amount",
        "widget": "text"
      }
    },
    "total1a": {
      "type": "string",
      "x-va-field": {
        "label": "Total1a",
        "widget": "text"
      }
    },
    "amount22": {
      "type": "string",
      "x-va-field": {
        "label": "Amount",
        "widget": "text"
      }
    },
    "amount23": {
      "type": "string",
      "x-va-field": {
        "label": "Amount",
        "widget": "text"
      }
    },
    "amount24": {
      "type": "string",
      "x-va-field": {
        "label": "Amount",
        "widget": "text"
      }
    },
    "amount25": {
      "type": "string",
      "x-va-field": {
        "label": "Amount",
        "widget": "text"
      }
    },
    "amount26": {
      "type": "string",
      "x-va-field": {
        "label": "Amount",
        "widget": "text"
      }
    },
    "amount27": {
      "type": "string",
      "x-va-field": {
        "label": "Amount",
        "widget": "text"
      }
    },
    "amount28": {
      "type": "string",
      "x-va-field": {
        "label": "Amount",
        "widget": "text"
      }
    },
    "amount29": {
      "type": "string",
      "x-va-field": {
        "label": "Amount",
        "widget": "text"
      }
    },
    "total1b": {
      "type": "string",
      "x-va-field": {
        "label": "Total1b",
        "widget": "text"
      }
    },
    "amount22a": {
      "type": "string",
      "x-va-field": {
        "label": "Amount22a",
        "widget": "text"
      }
    },
    "amount23a": {
      "type": "string",
      "x-va-field": {
        "label": "Amount23a",
        "widget": "text"
      }
    },
    "amount24a": {
      "type": "string",
      "x-va-field": {
        "label": "Amount24a",
        "widget": "text"
      }
    },
    "amount25a": {
      "type": "string",
      "x-va-field": {
        "label": "Amount25a",
        "widget": "text"
      }
    },
    "amount26a": {
      "type": "string",
      "x-va-field": {
        "label": "Amount26a",
        "widget": "text"
      }
    },
    "amount27a": {
      "type": "string",
      "x-va-field": {
        "label": "Amount27a",
        "widget": "text"
      }
    },
    "amount28a": {
      "type": "string",
      "x-va-field": {
        "label": "Amount28a",
        "widget": "text"
      }
    },
    "total1c": {
      "type": "string",
      "x-va-field": {
        "label": "Total1c",
        "widget": "text"
      }
    },
    "items1": {
      "type": "string",
      "x-va-field": {
        "label": "Items",
        "widget": "text"
      }
    },
    "items2": {
      "type": "string",
      "x-va-field": {
        "label": "Items",
        "widget": "text"
      }
    },
    "items3": {
      "type": "string",
      "x-va-field": {
        "label": "Items",
        "widget": "text"
      }
    },
    "items4": {
      "type": "string",
      "x-va-field": {
        "label": "Items",
        "widget": "text"
      }
    },
    "items5": {
      "type": "string",
      "x-va-field": {
        "label": "Items",
        "widget": "text"
      }
    },
    "items6": {
      "type": "string",
      "x-va-field": {
        "label": "Items",
        "widget": "text"
      }
    },
    "items7": {
      "type": "string",
      "x-va-field": {
        "label": "Items",
        "widget": "text"
      }
    },
    "total2": {
      "type": "string",
      "x-va-field": {
        "label": "Total",
        "widget": "text"
      }
    },
    "amount32": {
      "type": "string",
      "x-va-field": {
        "label": "Amount",
        "widget": "text"
      }
    },
    "amount32a": {
      "type": "string",
      "x-va-field": {
        "label": "Amount32a",
        "widget": "text"
      }
    },
    "amount33": {
      "type": "string",
      "x-va-field": {
        "label": "Amount",
        "widget": "text"
      }
    },
    "amount33a": {
      "type": "string",
      "x-va-field": {
        "label": "Amount33a",
        "widget": "text"
      }
    },
    "amount34": {
      "type": "string",
      "x-va-field": {
        "label": "Amount",
        "widget": "text"
      }
    },
    "amount35": {
      "type": "string",
      "x-va-field": {
        "label": "Amount",
        "widget": "text"
      }
    },
    "amount36": {
      "type": "string",
      "x-va-field": {
        "label": "Amount",
        "widget": "text"
      }
    },
    "amount34a": {
      "type": "string",
      "x-va-field": {
        "label": "Amount34a",
        "widget": "text"
      }
    },
    "amount35a": {
      "type": "string",
      "x-va-field": {
        "label": "Amount35a",
        "widget": "text"
      }
    },
    "amount36a": {
      "type": "string",
      "x-va-field": {
        "label": "Amount36a",
        "widget": "text"
      }
    },
    "total3a": {
      "type": "string",
      "x-va-field": {
        "label": "Total3a",
        "widget": "text"
      }
    },
    "total4a": {
      "type": "string",
      "x-va-field": {
        "label": "Total4a",
        "widget": "text"
      }
    },
    "total5a": {
      "type": "string",
      "x-va-field": {
        "label": "Total5a",
        "widget": "text"
      }
    },
    "total6a": {
      "type": "string",
      "x-va-field": {
        "label": "Total6a",
        "widget": "text"
      }
    },
    "total4b": {
      "type": "string",
      "x-va-field": {
        "label": "Total4b",
        "widget": "text"
      }
    },
    "total5b": {
      "type": "string",
      "x-va-field": {
        "label": "Total5b",
        "widget": "text"
      }
    },
    "total6b": {
      "type": "string",
      "x-va-field": {
        "label": "Total6b",
        "widget": "text"
      }
    },
    "total3c": {
      "type": "string",
      "x-va-field": {
        "label": "Total3c",
        "widget": "text"
      }
    },
    "total4c": {
      "type": "string",
      "x-va-field": {
        "label": "Total4c",
        "widget": "text"
      }
    },
    "total5c": {
      "type": "string",
      "x-va-field": {
        "label": "Total5c",
        "widget": "text"
      }
    },
    "total6c": {
      "type": "string",
      "x-va-field": {
        "label": "Total6c",
        "widget": "text"
      }
    },
    "total7": {
      "type": "string",
      "x-va-field": {
        "label": "Total",
        "widget": "text"
      }
    },
    "total8": {
      "type": "string",
      "x-va-field": {
        "label": "Total",
        "widget": "text"
      }
    },
    "total9": {
      "type": "string",
      "x-va-field": {
        "label": "Total",
        "widget": "text"
      }
    },
    "total10": {
      "type": "string",
      "x-va-field": {
        "label": "Total",
        "widget": "text"
      }
    },
    "total3b": {
      "type": "string",
      "x-va-field": {
        "label": "Total3b",
        "widget": "text"
      }
    },
    "signatureOfVaApprovedUnderwriter": {
      "type": "string",
      "x-va-field": {
        "label": "Signature of VA Approved Underwriter",
        "widget": "text"
      }
    },
    "incomeDebtRatio": {
      "type": "string",
      "x-va-field": {
        "label": "Income Debt Ratio",
        "widget": "text"
      }
    },
    "interest1": {
      "type": "string",
      "x-va-field": {
        "label": "Interest",
        "widget": "text"
      }
    },
    "applicantAge": {
      "type": "string",
      "x-va-field": {
        "label": "Applicant Age",
        "widget": "text"
      }
    },
    "spousesAge": {
      "type": "string",
      "x-va-field": {
        "label": "Spouses Age",
        "widget": "text"
      }
    },
    "signatureAndTitleOfApprovingOfficial": {
      "type": "string",
      "x-va-field": {
        "label": "Signature and Title of Approving Official",
        "widget": "text"
      }
    },
    "specifyother": {
      "type": "string",
      "x-va-field": {
        "label": "Specifyother",
        "widget": "text"
      }
    },
    "borrowerMedianCreditScore": {
      "type": "string",
      "x-va-field": {
        "label": "Borrower Median Credit Score",
        "widget": "text"
      }
    },
    "coBorrowerMedianCreditScore": {
      "type": "string",
      "x-va-field": {
        "label": "Co Borrower Median Credit Score",
        "widget": "text"
      }
    },
    "coBorrowerCaivrs": {
      "type": "string",
      "x-va-field": {
        "label": "Co Borrower Caivrs",
        "widget": "text"
      }
    },
    "borrowersCaivrs": {
      "type": "string",
      "x-va-field": {
        "label": "Borrowers Caivrs",
        "widget": "text"
      }
    },
    "remarks": {
      "type": "string",
      "x-va-field": {
        "label": "Remarks",
        "widget": "text"
      }
    },
    "vaapprovedUnderwriterId": {
      "type": "string",
      "x-va-field": {
        "label": "VA Approved Underwriter ID",
        "widget": "text"
      }
    },
    "nameOfBorrower_2AmountOfLoan": {
      "type": "string",
      "x-va-field": {
        "label": "Name of Borrower_2Amount of Loan",
        "widget": "text"
      }
    },
    "cashDownPaymentOnPurchase": {
      "type": "string",
      "x-va-field": {
        "label": "Cash Down Payment on Purchase",
        "widget": "text"
      }
    },
    "applicantSAge": {
      "type": "string",
      "x-va-field": {
        "label": "Applicant S Age",
        "widget": "text"
      }
    },
    "utilitiesIncluded": {
      "type": "string",
      "x-va-field": {
        "label": "Utilities Included",
        "widget": "text"
      }
    },
    "occupationOfApplicant2": {
      "type": "string",
      "x-va-field": {
        "label": "Occupation of Applicant",
        "widget": "text"
      }
    },
    "occupationOfSpouse2": {
      "type": "string",
      "x-va-field": {
        "label": "Occupation of Spouse",
        "widget": "text"
      }
    },
    "numberOfYearsAt": {
      "type": "string",
      "x-va-field": {
        "label": "Number of Years at",
        "widget": "text"
      }
    },
    "liquidAssets2": {
      "type": "string",
      "x-va-field": {
        "label": "Liquid Assets",
        "widget": "text"
      }
    },
    "currentMonthly": {
      "type": "string",
      "x-va-field": {
        "label": "Current Monthly",
        "widget": "text"
      }
    },
    "ageOfDependents2": {
      "type": "string",
      "x-va-field": {
        "label": "Age of Dependents",
        "widget": "text"
      }
    },
    "dateSigned_55SignatureOfVaApprovedUnderwriter": {
      "type": "string",
      "format": "date",
      "x-va-field": {
        "label": "Date Signed_55Signature of VA Approved Underwriter",
        "widget": "date"
      }
    },
    "finalAction_57DateSigned_58SignatureAndTitleOfApp": {
      "type": "string",
      "format": "date",
      "x-va-field": {
        "label": "Final Action_57Date Signed_58Signature and Title of App",
        "widget": "date"
      }
    },
    "wasAnAutomatedUnderwritingSystemUsed": {
      "type": "string",
      "x-va-field": {
        "label": "Was an Automated Underwriting System Used",
        "widget": "text"
      }
    },
    "termOfLoan": {
      "type": "string",
      "x-va-field": {
        "label": "Term of Loan",
        "widget": "text"
      }
    },
    "realtyTaxes": {
      "type": "string",
      "x-va-field": {
        "label": "Realty Taxes",
        "widget": "text"
      }
    },
    "stateIncomeTax": {
      "type": "string",
      "x-va-field": {
        "label": "State Income Tax",
        "widget": "select"
      }
    },
    "selectSystemUsedCheckAppropriateBox": {
      "type": "string",
      "x-va-field": {
        "label": "SELECT SYSTEM USED (Check appropriate box)",
        "widget": "text"
      }
    },
    "riskClassification": {
      "type": "string",
      "x-va-field": {
        "label": "Risk Classification",
        "widget": "text"
      }
    },
    "borrowerMedianCreditScore47BorrowerCaivrs48CoBorrow": {
      "type": "string",
      "x-va-field": {
        "label": "Borrower Median Credit Score47. Borrower Caivrs48. Co-Borrow",
        "widget": "text"
      }
    },
    "pastCreditRecord": {
      "type": "string",
      "x-va-field": {
        "label": "Past Credit Record",
        "widget": "text"
      }
    },
    "doesLoanMeetVaCreditStandardsGiveReasonsFor": {
      "type": "string",
      "x-va-field": {
        "label": "DOES LOAN MEET VA CREDIT STANDARDS? (Give reasons for",
        "widget": "text"
      }
    },
    "remarksIfAdditionalSpaceIsNeededUseReverseOrAttac": {
      "type": "string",
      "x-va-field": {
        "label": "REMARKS (If additional space is needed, use reverse or attac",
        "widget": "text"
      }
    }
  },
  "x-va-metadata": {
    "formUrl": "https://www.vba.va.gov/pubs/forms/vba-26-6393-are.pdf",
    "status": "digitized",
    "totalFields": 120,
    "composedFields": 108,
    "coveragePercent": 100,
    "xfaLabelCount": 0,
    "needsReviewCount": 0,
    "pageCount": 1,
    "generatedAt": "2026-03-28T17:33:17.232Z",
    "redigitizedAt": "2026-03-30T20:37:17.741Z",
    "extractionSources": [
      "acroform",
      "acroform+text-inference",
      "text-inference"
    ],
    "fieldNameFixedAt": "2026-03-30T23:47:24.168348+00:00"
  }
}