{
  "$schema": "http://json-schema.org/draft-07/schema#",
  "title": "VA Form 40-10190",
  "type": "object",
  "properties": {
    "nameOfDeceased": {
      "type": "string",
      "description": "Name of deceased veteran",
      "x-va-field": {
        "label": "Name of Deceased"
      }
    },
    "dateOfDeath": {
      "type": "string",
      "format": "date",
      "description": "Date of death",
      "x-va-field": {
        "label": "Date of Death"
      }
    },
    "vaFileNumber": {
      "type": "string",
      "description": "VA file number",
      "x-va-field": {
        "label": "VA File Number"
      }
    },
    "socialSecurityNumber": {
      "type": "string",
      "description": "Social Security Number",
      "x-va-field": {
        "label": "Social Security Number"
      }
    },
    "dateOfBirth": {
      "type": "string",
      "format": "date",
      "description": "Date of birth",
      "x-va-field": {
        "label": "Date of Birth"
      }
    },
    "cemeteryName": {
      "type": "string",
      "description": "Name of cemetery for burial",
      "x-va-field": {
        "label": "Cemetery Name"
      }
    },
    "burialLocation": {
      "type": "string",
      "description": "Burial location/lot number",
      "x-va-field": {
        "label": "Burial Location"
      }
    },
    "address": {
      "type": "object",
      "properties": {
        "street": {
          "type": "string",
          "maxLength": 50
        },
        "city": {
          "type": "string",
          "maxLength": 30
        },
        "state": {
          "type": "string",
          "maxLength": 2
        },
        "postalCode": {
          "type": "string",
          "maxLength": 10
        }
      },
      "required": [
        "street",
        "city",
        "state",
        "postalCode"
      ],
      "x-va-field": {
        "label": "Address"
      }
    },
    "relationshipToDeceased": {
      "type": "string",
      "description": "Claimant's relationship to deceased",
      "x-va-field": {
        "label": "Relationship to Deceased"
      }
    },
    "applicantName": {
      "type": "string",
      "description": "Applicant's full name",
      "x-va-field": {
        "label": "Applicant Name"
      }
    },
    "phoneNumber": {
      "type": "string",
      "description": "Contact phone number",
      "x-va-field": {
        "label": "Phone Number"
      }
    },
    "dateOfApplication": {
      "type": "string",
      "format": "date",
      "description": "Date of application",
      "x-va-field": {
        "label": "Date of Application"
      }
    }
  },
  "x-va-metadata": {
    "formUrl": "https://www.va.gov/vaforms/va/pdf/VA40-10190.pdf",
    "totalFields": 12,
    "composedFields": 12,
    "coveragePercent": 100,
    "xfaLabelCount": 0,
    "needsReviewCount": 0,
    "status": "digitized",
    "pageCount": 2,
    "generatedAt": "2026-03-29T14:14:58.000Z",
    "generationMethod": "template-based-inference",
    "fieldNameFixedAt": "2026-03-30T21:38:04.858143+00:00"
  }
}